gyxi/__init__.py
gyxi/client.py
gyxi-0.1.7.dist-info/WHEEL
gyxi-0.1.7.dist-info/METADATA
gyxi-0.1.7.dist-info/RECORD
