Metadata-Version: 2.1
Name: gyxi
Version: 0.1.7
Summary: Gyxi API Client
Author: gabluc
Author-email: gabluc@protonmail.com
Requires-Python: >=3.5,<4.0
Classifier: Programming Language :: Python :: 3
Classifier: Programming Language :: Python :: 3.5
Classifier: Programming Language :: Python :: 3.6
Classifier: Programming Language :: Python :: 3.7
Classifier: Programming Language :: Python :: 3.8
Requires-Dist: attrs (>=19.3.0,<20.0.0)
Requires-Dist: requests (>=2.23.0,<3.0.0)
